tkdocs/__init__.py
tkdocs/tkdocs.py
tkdocs-0.0.6.dist-info/licenses/LICENSE.md
tkdocs-0.0.6.dist-info/METADATA
tkdocs-0.0.6.dist-info/WHEEL
tkdocs-0.0.6.dist-info/top_level.txt
tkdocs-0.0.6.dist-info/RECORD
