Metadata-Version: 2.4
Name: tkdocs
Version: 0.0.6
Summary: Download and parse parliamentary documents from the Dutch Lower House website
Author-email: dirkmjk <info@dirkmjk.nl>
Project-URL: Homepage, https://github.com/DIRKMJK/tkdocs
Classifier: License :: OSI Approved :: MIT License
Classifier: Programming Language :: Python
Classifier: Programming Language :: Python :: 3
License-File: LICENSE.md
Requires-Dist: python-dateutil
Requires-Dist: pandas
Requires-Dist: requests
Requires-Dist: bs4
Dynamic: license-file
